fastpyvectordb/__init__.py
fastpyvectordb/binary_persistence.py
fastpyvectordb/client.py
fastpyvectordb/embeddings.py
fastpyvectordb/graph.py
fastpyvectordb/hybrid_graph_vector.py
fastpyvectordb/hybrid_search.py
fastpyvectordb/parallel_search.py
fastpyvectordb/py.typed
fastpyvectordb/quantization.py
fastpyvectordb/realtime.py
fastpyvectordb/server.py
fastpyvectordb/server_full.py
fastpyvectordb/vectordb.py
fastpyvectordb/vectordb_optimized.py
fastpyvectordb-0.1.0.dist-info/LICENSE
fastpyvectordb-0.1.0.dist-info/METADATA
fastpyvectordb-0.1.0.dist-info/WHEEL
fastpyvectordb-0.1.0.dist-info/entry_points.txt
fastpyvectordb-0.1.0.dist-info/top_level.txt
fastpyvectordb-0.1.0.dist-info/RECORD
