Metadata-Version: 2.1
Name: fastpyvectordb
Version: 0.1.0
Summary: A high-performance Python vector database for semantic search and RAG applications
Author: FastPyDB Contributors
Project-URL: Homepage, https://github.com/jcolano/custom-python-vectordb
Project-URL: Documentation, https://github.com/jcolano/custom-python-vectordb#readme
Project-URL: Repository, https://github.com/jcolano/custom-python-vectordb
Project-URL: Issues, https://github.com/jcolano/custom-python-vectordb/issues
Keywords: vector-database,embeddings,semantic-search,similarity-search,HNSW,RAG,retrieval,machine-learning,AI,NLP
Classifier: Development Status :: 4 - Beta
Classifier: Intended Audience :: Developers
Classifier: Intended Audience :: Science/Research
Classifier: License :: OSI Approved :: MIT License
Classifier: Operating System :: OS Independent
Classifier: Programming Language :: Python :: 3
Classifier: Programming Language :: Python :: 3.10
Classifier: Programming Language :: Python :: 3.11
Classifier: Programming Language :: Python :: 3.12
Classifier: Topic :: Scientific/Engineering :: Artificial Intelligence
Classifier: Topic :: Database
Classifier: Topic :: Text Processing :: Indexing
Requires-Python: >=3.10
License-File: LICENSE
Requires-Dist: numpy>=1.24.0
Requires-Dist: hnswlib>=0.8.0
Provides-Extra: all
Requires-Dist: sentence-transformers>=2.2.0; extra == "all"
Requires-Dist: openai>=1.0.0; extra == "all"
Requires-Dist: cohere>=4.0.0; extra == "all"
Requires-Dist: fastapi>=0.109.0; extra == "all"
Requires-Dist: uvicorn[standard]>=0.27.0; extra == "all"
Requires-Dist: pydantic>=2.0.0; extra == "all"
Requires-Dist: websockets>=12.0; extra == "all"
Requires-Dist: httpx>=0.26.0; extra == "all"
Requires-Dist: requests>=2.31.0; extra == "all"
Requires-Dist: networkx>=3.0; extra == "all"
Provides-Extra: client
Requires-Dist: httpx>=0.26.0; extra == "client"
Requires-Dist: requests>=2.31.0; extra == "client"
Provides-Extra: cohere
Requires-Dist: cohere>=4.0.0; extra == "cohere"
Provides-Extra: dev
Requires-Dist: pytest>=7.0.0; extra == "dev"
Requires-Dist: pytest-cov>=4.0.0; extra == "dev"
Requires-Dist: black>=23.0.0; extra == "dev"
Requires-Dist: ruff>=0.1.0; extra == "dev"
Requires-Dist: mypy>=1.0.0; extra == "dev"
Provides-Extra: graph
Requires-Dist: networkx>=3.0; extra == "graph"
Provides-Extra: local
Requires-Dist: sentence-transformers>=2.2.0; extra == "local"
Provides-Extra: openai
Requires-Dist: openai>=1.0.0; extra == "openai"
Provides-Extra: server
Requires-Dist: fastapi>=0.109.0; extra == "server"
Requires-Dist: uvicorn[standard]>=0.27.0; extra == "server"
Requires-Dist: pydantic>=2.0.0; extra == "server"
Requires-Dist: websockets>=12.0; extra == "server"
